{"images": [{"id": 0, "file_name": "00000.jpg", "height": 720, "width": 1280}, {"id": 0, "file_name": "00000.jpg", "height": 720, "width": 1280}, {"id": 1, "file_name": "00001.jpg", "height": 720, "width": 1280}, {"id": 2, "file_name": "00002.jpg", "height": 720, "width": 1280}, {"id": 3, "file_name": "00003.jpg", "height": 720, "width": 1280}, {"id": 4, "file_name": "00004.jpg", "height": 720, "width": 1280}, {"id": 5, "file_name": "00005.jpg", "height": 720, "width": 1280}, {"id": 6, "file_name": "00006.jpg", "height": 720, "width": 1280}, {"id": 7, "file_name": "00007.jpg", "height": 720, "width": 1280}, {"id": 8, "file_name": "00008.jpg", "height": 720, "width": 1280}, {"id": 9, "file_name": "00009.jpg", "height": 720, "width": 1280}, {"id": 10, "file_name": "00010.jpg", "height": 720, "width": 1280}, {"id": 11, "file_name": "00011.jpg", "height": 720, "width": 1280}, {"id": 12, "file_name": "00012.jpg", "height": 720, "width": 1280}, {"id": 13, "file_name": "00013.jpg", "height": 720, "width": 1280}, {"id": 14, "file_name": "00014.jpg", "height": 720, "width": 1280}, {"id": 15, "file_name": "00015.jpg", "height": 720, "width": 1280}, {"id": 16, "file_name": "00016.jpg", "height": 720, "width": 1280}, {"id": 17, "file_name": "00017.jpg", "height": 720, "width": 1280}, {"id": 18, "file_name": "00018.jpg", "height": 720, "width": 1280}, {"id": 19, "file_name": "00019.jpg", "height": 720, "width": 1280}, {"id": 20, "file_name": "00020.jpg", "height": 720, "width": 1280}, {"id": 21, "file_name": "00021.jpg", "height": 720, "width": 1280}, {"id": 22, "file_name": "00022.jpg", "height": 720, "width": 1280}, {"id": 23, "file_name": "00023.jpg", "height": 720, "width": 1280}, {"id": 24, "file_name": "00024.jpg", "height": 720, "width": 1280}, {"id": 25, "file_name": "00025.jpg", "height": 720, "width": 1280}, {"id": 26, "file_name": "00026.jpg", "height": 720, "width": 1280}, {"id": 27, "file_name": "00027.jpg", "height": 720, "width": 1280}, {"id": 28, "file_name": "00028.jpg", "height": 720, "width": 1280}, {"id": 29, "file_name": "00029.jpg", "height": 720, "width": 1280}, {"id": 30, "file_name": "00030.jpg", "height": 720, "width": 1280}, {"id": 31, "file_name": "00031.jpg", "height": 720, "width": 1280}, {"id": 32, "file_name": "00032.jpg", "height": 720, "width": 1280}, {"id": 33, "file_name": "00033.jpg", "height": 720, "width": 1280}, {"id": 34, "file_name": "00034.jpg", "height": 720, "width": 1280}, {"id": 35, "file_name": "00035.jpg", "height": 720, "width": 1280}, {"id": 36, "file_name": "00036.jpg", "height": 720, "width": 1280}, {"id": 37, "file_name": "00037.jpg", "height": 720, "width": 1280}, {"id": 38, "file_name": "00038.jpg", "height": 720, "width": 1280}, {"id": 39, "file_name": "00039.jpg", "height": 720, "width": 1280}, {"id": 40, "file_name": "00040.jpg", "height": 720, "width": 1280}, {"id": 41, "file_name": "00041.jpg", "height": 720, "width": 1280}, {"id": 42, "file_name": "00042.jpg", "height": 720, "width": 1280}, {"id": 43, "file_name": "00043.jpg", "height": 720, "width": 1280}, {"id": 44, "file_name": "00044.jpg", "height": 720, "width": 1280}, {"id": 45, "file_name": "00045.jpg", "height": 720, "width": 1280}, {"id": 46, "file_name": "00046.jpg", "height": 720, "width": 1280}, {"id": 47, "file_name": "00047.jpg", "height": 720, "width": 1280}, {"id": 48, "file_name": "00048.jpg", "height": 720, "width": 1280}, {"id": 49, "file_name": "00049.jpg", "height": 720, "width": 1280}, {"id": 50, "file_name": "00050.jpg", "height": 720, "width": 1280}, {"id": 51, "file_name": "00051.jpg", "height": 720, "width": 1280}, {"id": 52, "file_name": "00052.jpg", "height": 720, "width": 1280}, {"id": 53, "file_name": "00053.jpg", "height": 720, "width": 1280}, {"id": 54, "file_name": "00054.jpg", "height": 720, "width": 1280}, {"id": 55, "file_name": "00055.jpg", "height": 720, "width": 1280}, {"id": 56, "file_name": "00056.jpg", "height": 720, "width": 1280}, {"id": 57, "file_name": "00057.jpg", "height": 720, "width": 1280}, {"id": 58, "file_name": "00058.jpg", "height": 720, "width": 1280}, {"id": 59, "file_name": "00059.jpg", "height": 720, "width": 1280}, {"id": 60, "file_name": "00060.jpg", "height": 720, "width": 1280}, {"id": 61, "file_name": "00061.jpg", "height": 720, "width": 1280}, {"id": 62, "file_name": "00062.jpg", "height": 720, "width": 1280}, {"id": 63, "file_name": "00063.jpg", "height": 720, "width": 1280}, {"id": 64, "file_name": "00064.jpg", "height": 720, "width": 1280}, {"id": 65, "file_name": "00065.jpg", "height": 720, "width": 1280}, {"id": 66, "file_name": "00066.jpg", "height": 720, "width": 1280}, {"id": 67, "file_name": "00067.jpg", "height": 720, "width": 1280}, {"id": 68, "file_name": "00068.jpg", "height": 720, "width": 1280}, {"id": 69, "file_name": "00069.jpg", "height": 720, "width": 1280}, {"id": 70, "file_name": "00070.jpg", "height": 720, "width": 1280}, {"id": 71, "file_name": "00071.jpg", "height": 720, "width": 1280}, {"id": 72, "file_name": "00072.jpg", "height": 720, "width": 1280}, {"id": 73, "file_name": "00073.jpg", "height": 720, "width": 1280}, {"id": 74, "file_name": "00074.jpg", "height": 720, "width": 1280}, {"id": 75, "file_name": "00075.jpg", "height": 720, "width": 1280}, {"id": 76, "file_name": "00076.jpg", "height": 720, "width": 1280}, {"id": 77, "file_name": "00077.jpg", "height": 720, "width": 1280}, {"id": 78, "file_name": "00078.jpg", "height": 720, "width": 1280}, {"id": 79, "file_name": "00079.jpg", "height": 720, "width": 1280}, {"id": 80, "file_name": "00080.jpg", "height": 720, "width": 1280}, {"id": 81, "file_name": "00081.jpg", "height": 720, "width": 1280}, {"id": 82, "file_name": "00082.jpg", "height": 720, "width": 1280}, {"id": 83, "file_name": "00083.jpg", "height": 720, "width": 1280}, {"id": 84, "file_name": "00084.jpg", "height": 720, "width": 1280}, {"id": 85, "file_name": "00085.jpg", "height": 720, "width": 1280}, {"id": 86, "file_name": "00086.jpg", "height": 720, "width": 1280}, {"id": 87, "file_name": "00087.jpg", "height": 720, "width": 1280}, {"id": 88, "file_name": "00088.jpg", "height": 720, "width": 1280}, {"id": 89, "file_name": "00089.jpg", "height": 720, "width": 1280}, {"id": 90, "file_name": "00090.jpg", "height": 720, "width": 1280}, {"id": 91, "file_name": "00091.jpg", "height": 720, "width": 1280}, {"id": 92, "file_name": "00092.jpg", "height": 720, "width": 1280}, {"id": 93, "file_name": "00093.jpg", "height": 720, "width": 1280}, {"id": 94, "file_name": "00094.jpg", "height": 720, "width": 1280}, {"id": 95, "file_name": "00095.jpg", "height": 720, "width": 1280}, {"id": 96, "file_name": "00096.jpg", "height": 720, "width": 1280}, {"id": 97, "file_name": "00097.jpg", "height": 720, "width": 1280}, {"id": 98, "file_name": "00098.jpg", "height": 720, "width": 1280}, {"id": 99, "file_name": "00099.jpg", "height": 720, "width": 1280}, {"id": 100, "file_name": "00100.jpg", "height": 720, "width": 1280}, {"id": 101, "file_name": "00101.jpg", "height": 720, "width": 1280}, {"id": 102, "file_name": "00102.jpg", "height": 720, "width": 1280}, {"id": 103, "file_name": "00103.jpg", "height": 720, "width": 1280}, {"id": 104, "file_name": "00104.jpg", "height": 720, "width": 1280}, {"id": 105, "file_name": "00105.jpg", "height": 720, "width": 1280}, {"id": 106, "file_name": "00106.jpg", "height": 720, "width": 1280}, {"id": 107, "file_name": "00107.jpg", "height": 720, "width": 1280}, {"id": 108, "file_name": "00108.jpg", "height": 720, "width": 1280}, {"id": 109, "file_name": "00109.jpg", "height": 720, "width": 1280}, {"id": 110, "file_name": "00110.jpg", "height": 720, "width": 1280}], "annotations": [{"image_id": 0, "category_id": 1, "id": 0, "segmentation": {"size": [720, 1280], "counts": "n`ja0=Pf07K2N2M4M2N2O1N101N101O0O100000000000O1000001O0O10001O1N1O2N2O1M3N3L2N6Jc^_9"}, "area": 1147, "bbox": [811, 290, 37, 38], "iscrowd": 0}, {"image_id": 0, "category_id": 1, "id": 0, "segmentation": {"size": [720, 1280], "counts": "n`ja0=Pf07K2N2M4M2N2O1N101N101O0O100000000000O1000001O0O10001O1N1O2N2O1M3N3L2N6Jc^_9"}, "area": 1147, "bbox": [811, 290, 37, 38], "iscrowd": 0}, {"image_id": 1, "category_id": 1, "id": 1, "segmentation": {"size": [720, 1280], "counts": "PTia0;Sf04L4L4L3N2N2N2O2M101N1000000O101O0000O100000001O000O2O001N2N2O1M202L3M3M6J5J`^_9"}, "area": 1186, "bbox": [809, 290, 39, 39], "iscrowd": 0}, {"image_id": 2, "category_id": 1, "id": 2, "segmentation": {"size": [720, 1280], "counts": "a]ha0;Rf05L4M2M4M2N2N2N2O1N101O0O100000000000000000000001O0O101O0O2O1N2N2M3N2M5K4Kck`9"}, "area": 1189, "bbox": [808, 291, 38, 38], "iscrowd": 0}, {"image_id": 3, "category_id": 1, "id": 3, "segmentation": {"size": [720, 1280], "counts": "Qgga0<Qf06L2M3N2M3N2O1N2N2O1N10000O2O00000000000000O2O0000001N101N101N2N2N3L3N3L4JTba9"}, "area": 1195, "bbox": [807, 291, 38, 39], "iscrowd": 0}, {"image_id": 4, "category_id": 1, "id": 4, "segmentation": {"size": [720, 1280], "counts": "bPga0;Rf06K3M3N2N3M2N2N101N2O000O2O0000000000000000000001O0O101O0O2O1N2N2N2M3M4M3IeXb9"}, "area": 1189, "bbox": [806, 292, 38, 38], "iscrowd": 0}, {"image_id": 5, "category_id": 1, "id": 5, "segmentation": {"size": [720, 1280], "counts": "TZfa09Sf06K6K3N2N2N2O1N2N2O0O2O000O2O000000000000000001N10001O0O2O0O2N102M2M3M3M4LSob9"}, "area": 1208, "bbox": [805, 292, 38, 39], "iscrowd": 0}, {"image_id": 6, "category_id": 1, "id": 6, "segmentation": {"size": [720, 1280], "counts": "gcea04Xf08H6L4L3N2N2N2O1N2N101N101O00000O10000001O0000000O101O001N101N1O2N2N3L3M4L6HQob9"}, "area": 1202, "bbox": [804, 292, 39, 39], "iscrowd": 0}, {"image_id": 7, "category_id": 1, "id": 7, "segmentation": {"size": [720, 1280], "counts": "Wmda05Vf09J4L3M4M2N2N2N2N101N101O0O100000000000000000000001N100O2O001N2N2N2N3M2L6L7F]ec9"}, "area": 1191, "bbox": [803, 293, 39, 38], "iscrowd": 0}, {"image_id": 8, "category_id": 1, "id": 8, "segmentation": {"size": [720, 1280], "counts": "U`ca0:Rf07J5M2M4M2O1N1O2N101N100000000O10000001O00000O10001O0O2O0O2O1N2N2N3M2M4L:Fihe9"}, "area": 1162, "bbox": [801, 293, 38, 38], "iscrowd": 0}, {"image_id": 9, "category_id": 1, "id": 9, "segmentation": {"size": [720, 1280], "counts": "W_\\a05Uf0:J4L3N3M2N2N2N2N2O1N101O0O100000000000000001O0O10001N101N101N2N2N3N1N2L5LQjl9"}, "area": 1195, "bbox": [791, 293, 38, 39], "iscrowd": 0}, {"image_id": 10, "category_id": 1, "id": 10, "segmentation": {"size": [720, 1280], "counts": "iZSa01Wf0=J3L4L4M2N2N2N101N2O001N101O000O10001OO10001O00000O2O0O101O1N1O2O1M4N1M4M3LPXU:"}, "area": 1214, "bbox": [778, 293, 39, 40], "iscrowd": 0}, {"image_id": 11, "category_id": 1, "id": 11, "segmentation": {"size": [720, 1280], "counts": "b_i`0;Sf05K4L3N2N2N2N2N2O0O2O001N10001O00000000000000O10001N100O2O1N1O2N2N2M4M3K7Hai_:"}, "area": 1160, "bbox": [764, 293, 38, 38], "iscrowd": 0}, {"image_id": 12, "category_id": 1, "id": 12, "segmentation": {"size": [720, 1280], "counts": "iW^`01Yf0;H5M2M4M2N2N2O1N2N101N2O001N10000000000000000000O2O000O2O0O2N2N2N2N2M4M3L5JoZj:"}, "area": 1159, "bbox": [748, 294, 39, 38], "iscrowd": 0}, {"image_id": 13, "category_id": 1, "id": 13, "segmentation": {"size": [720, 1280], "counts": "USU`0;Sf05K4M3L3N2O0O2N2O0O2N2O000O101O0000000000O10001O0O101O0O2O1N2N2M3N2M4L5K]lT;"}, "area": 1122, "bbox": [735, 296, 37, 38], "iscrowd": 0}, {"image_id": 14, "category_id": 1, "id": 14, "segmentation": {"size": [720, 1280], "counts": "Vel?8Vf05J5M3L3N2N2N2N1O2O0O2O1O0O101O000000000000000000O2N100O2O1N1O2N2N2N3L4L4L6H]m[;"}, "area": 1154, "bbox": [723, 295, 39, 38], "iscrowd": 0}, {"image_id": 15, "category_id": 1, "id": 15, "segmentation": {"size": [720, 1280], "counts": "emd?8Uf07J6J4M3M2N1O101N100O101O0O100000000O1001O0000001O0O2N101N2O1N2N2N2M4L5J6J\\[d;"}, "area": 1137, "bbox": [712, 294, 38, 38], "iscrowd": 0}, {"image_id": 16, "category_id": 1, "id": 16, "segmentation": {"size": [720, 1280], "counts": "[V]?5Tf0:K4L4M2N2N2N1O2N2O1N2O001N1000000001O000000000O101O001N101N2O1N2M3N2N3L7EnRl;"}, "area": 1174, "bbox": [701, 296, 38, 39], "iscrowd": 0}, {"image_id": 17, "category_id": 1, "id": 17, "segmentation": {"size": [720, 1280], "counts": "gkV?8Uf06K5K4L4M2O1N1O2N1O2O00001N100000001O000000O2O00001N101N1O2O1M2O2N2N3L5IPTS<"}, "area": 1150, "bbox": [692, 296, 37, 39], "iscrowd": 0}, {"image_id": 18, "category_id": 1, "id": 18, "segmentation": {"size": [720, 1280], "counts": "XaP?7Uf08I5M4L2N1O2N2N1O2O001N100O101O0000000000000000O2O001N1O2O0O2N2N2N3L4L4L4JngX<"}, "area": 1143, "bbox": [683, 296, 38, 38], "iscrowd": 0}, {"image_id": 19, "category_id": 1, "id": 19, "segmentation": {"size": [720, 1280], "counts": "eck>=Pf05M3M2N4L3M2N1O2O0O101N1000000000000000000001N100O101N101N2N2N1O2M5K5K8Ej[^<"}, "area": 1135, "bbox": [676, 297, 37, 38], "iscrowd": 0}, {"image_id": 20, "category_id": 1, "id": 20, "segmentation": {"size": [720, 1280], "counts": "d\\g>8Tf07K4L4L3N2N2N2O0O2O1O1N2O0000001O0000O1000000O10001O0O2N2N1O2M3N2M4M2M4K4Lbla<"}, "area": 1142, "bbox": [670, 293, 38, 39], "iscrowd": 0}, {"image_id": 21, "category_id": 1, "id": 21, "segmentation": {"size": [720, 1280], "counts": "kef>`0le06L3N3M2N2N101O0O2O000000001O00000O11O0O10000O101N101N101N2O1N2N2M4L6IVPd<"}, "area": 1118, "bbox": [669, 287, 36, 38], "iscrowd": 0}, {"image_id": 22, "category_id": 1, "id": 22, "segmentation": {"size": [720, 1280], "counts": "lXe>8Uf09H5L2M3N2N1N3N2O1N1O2O0O101O000000000001O00001O001N101O1N2O1N2N3M3F[ZOCje05`]e<"}, "area": 1191, "bbox": [667, 284, 36, 41], "iscrowd": 0}, {"image_id": 23, "category_id": 1, "id": 23, "segmentation": {"size": [720, 1280], "counts": "V`i>2Uf0;K4M3L4N2N2M3N1O2N1O10000O2OO1000000000000O101O00001N1O2N101N2O1N3L3L6K4JZi_<"}, "area": 1105, "bbox": [673, 284, 38, 38], "iscrowd": 0}, {"image_id": 24, "category_id": 1, "id": 24, "segmentation": {"size": [720, 1280], "counts": "\\Zl>1Y`30nUM;I5M2N3N2N1N3N2O0N3O0O1000001O0O10000001O0000001O1O0O2O1N1O2N3L2O3L3MjkZ<"}, "area": 1018, "bbox": [677, 285, 41, 36], "iscrowd": 0}, {"image_id": 25, "category_id": 1, "id": 25, "segmentation": {"size": [720, 1280], "counts": "`kV?9Sf06L4L3M3N2N2N1O2O1O1O000O2O00001O00000001O00000O2O1N1O2N2O1N2N2N2M4L5JdjS<"}, "area": 1048, "bbox": [692, 289, 36, 37], "iscrowd": 0}, {"image_id": 26, "category_id": 1, "id": 26, "segmentation": {"size": [720, 1280], "counts": "iR[?2Xf08K4N3M2M4M2N2O1N2O1N2O0O2O00001O0O10000001O0000001N100O2O0O2O1N2N2N2N3L3M4JQ`m;"}, "area": 1097, "bbox": [698, 294, 39, 37], "iscrowd": 0}, {"image_id": 27, "category_id": 1, "id": 27, "segmentation": {"size": [720, 1280], "counts": "\\]a?6Wf05L4L5L3L201N3M2O1N2O001N100000000O10000000000001O0O101O001N101M3N2N2N3M3K<BTUg;"}, "area": 1138, "bbox": [707, 301, 39, 37], "iscrowd": 0}, {"image_id": 28, "category_id": 1, "id": 28, "segmentation": {"size": [720, 1280], "counts": "[Wd?6Uf07L5K3N5K1O2N101N101O0O2O0O2O00000O2O000000000000O101O0O2O0O2N2O0O2N2N2M4M3L5Jkdc;"}, "area": 1224, "bbox": [711, 298, 40, 39], "iscrowd": 0}, {"image_id": 29, "category_id": 1, "id": 29, "segmentation": {"size": [720, 1280], "counts": "fgg?5Xf08I6K5K2N1O2N2N1O2O0O10001N100000000O010001O0000001N101O0O2N101N2N2N2N2M5K5Jmj`;"}, "area": 1154, "bbox": [716, 295, 39, 38], "iscrowd": 0}, {"image_id": 30, "category_id": 1, "id": 30, "segmentation": {"size": [720, 1280], "counts": "bnk??oe04L3N3M2N2N101N2N1O101O0O101O000000O1000001O000O101O0O2N2O1N1O3M2N2N2M6IoP^;"}, "area": 1127, "bbox": [722, 294, 37, 38], "iscrowd": 0}, {"image_id": 31, "category_id": 1, "id": 31, "segmentation": {"size": [720, 1280], "counts": "XRn?7Tf08K3M3N2M3N2N2N2O0O2O1N101O0000001OO1000000000000O2O0O101N101N2N2O2M2M3M3M8F]`Z;"}, "area": 1153, "bbox": [725, 295, 39, 38], "iscrowd": 0}, {"image_id": 32, "category_id": 1, "id": 32, "segmentation": {"size": [720, 1280], "counts": "iUP`02[f08I5K4L3M3N2O2M2O0O2O0O2O0O2O0000000O20N10000000000O101O0O101N2N2N2O1M3N3M3L7G[fW;"}, "area": 1171, "bbox": [728, 296, 40, 39], "iscrowd": 0}, {"image_id": 33, "category_id": 1, "id": 33, "segmentation": {"size": [720, 1280], "counts": "_fS`01Wf0>H6J3N3M102M2N101N100O100O100000000000000001O000O2O0O2O001N2N1O2N2N3L4L4KjbU;"}, "area": 1135, "bbox": [733, 300, 38, 37], "iscrowd": 0}, {"image_id": 34, "category_id": 1, "id": 34, "segmentation": {"size": [720, 1280], "counts": "mVW`0:Sf07J4L3N3M2N2N101N100O101O0O1000000000000000000001N101O001N2O0O2N3M2N2M4L4JXRR;"}, "area": 1159, "bbox": [738, 303, 38, 37], "iscrowd": 0}, {"image_id": 35, "category_id": 1, "id": 35, "segmentation": {"size": [720, 1280], "counts": "ZgZ`0;Sf05K4L4M3M2N2N2O0O2O0O10000O2O00000000000000O2O00001N101N101N2N2N2M4M3L4L4Jhan:"}, "area": 1144, "bbox": [743, 301, 38, 38], "iscrowd": 0}, {"image_id": 36, "category_id": 1, "id": 36, "segmentation": {"size": [720, 1280], "counts": "iW^`0<Rf05L3L3N3M2N2N1O2O1N100O101O0000000000000000000000O2O000O2O1N2N2N2N2N2M5K5JXQk:"}, "area": 1156, "bbox": [748, 301, 38, 37], "iscrowd": 0}, {"image_id": 37, "category_id": 1, "id": 37, "segmentation": {"size": [720, 1280], "counts": "Zha`0=Qf05L3L3N2N2O1N2N2O0O1O101N1000000000000000000001O0O101O0O101N2O1N2M3N3L4L5Jg`g:"}, "area": 1154, "bbox": [753, 302, 38, 37], "iscrowd": 0}, {"image_id": 38, "category_id": 1, "id": 38, "segmentation": {"size": [720, 1280], "counts": "bbd`06Wf06H6M4M3M1O2O1N1O2O1O0O101O00001N1000000001O000000001N101N101N2N2N2N2N3K6K6FTPd:"}, "area": 1127, "bbox": [757, 305, 39, 37], "iscrowd": 0}, {"image_id": 39, "category_id": 1, "id": 39, "segmentation": {"size": [720, 1280], "counts": "PSh`08Uf05L5K4M2M3N2N2N101N101O0O2O00000000001O00O10001O000O2O0O1O2O1N101N3M2M4L5JUVa:"}, "area": 1145, "bbox": [762, 305, 38, 38], "iscrowd": 0}, {"image_id": 40, "category_id": 1, "id": 40, "segmentation": {"size": [720, 1280], "counts": "]ck`0:Tf03N3M3M4L3M1O2N1O2N100O101O0O100010O00000000001O000O2O001N101N2N2O1M3N4K5Jde]:"}, "area": 1104, "bbox": [767, 304, 38, 37], "iscrowd": 0}, {"image_id": 41, "category_id": 1, "id": 41, "segmentation": {"size": [720, 1280], "counts": "]kVa07Vf07J3N2N5K3M2N2N101N2O0O101O000000000000000000000001N101N101N101N2O1N2M3M4M4JVgQ:"}, "area": 1172, "bbox": [783, 304, 39, 37], "iscrowd": 0}, {"image_id": 42, "category_id": 1, "id": 42, "segmentation": {"size": [720, 1280], "counts": "Pjba07Tf07L4L4M3M2N2N2N101N101N10001O000O100000000001O00000O2O001N101N2O0O2N2N3L3N4J:EQRe9"}, "area": 1198, "bbox": [800, 303, 40, 38], "iscrowd": 0}, {"image_id": 43, "category_id": 1, "id": 43, "segmentation": {"size": [720, 1280], "counts": "n^oa0=Qf03M5L3L2O2N2N2O1N101N101O0O10000000001O00000001N101O0O101N2O0O2O1N2N2N3L3M4L7FR]X9"}, "area": 1224, "bbox": [818, 305, 40, 39], "iscrowd": 0}, {"image_id": 44, "category_id": 1, "id": 44, "segmentation": {"size": [720, 1280], "counts": "e][b05Wf09J3L4M3L3N2N2O1N2O1N101O0O10001O0000000000000000O1000001N2N101N2N1O2O1N3M3L4L6Gogk8"}, "area": 1270, "bbox": [835, 310, 41, 39], "iscrowd": 0}, {"image_id": 45, "category_id": 1, "id": 45, "segmentation": {"size": [720, 1280], "counts": "mRhb04Uf0:J6K3N3M2O1N2N2N2O0O2O0O101O0000000O11O00000000000O2O001O0O2O1N101N2N3M2M4M3K\\i_8"}, "area": 1278, "bbox": [853, 313, 40, 40], "iscrowd": 0}, {"image_id": 46, "category_id": 1, "id": 46, "segmentation": {"size": [720, 1280], "counts": "dmQc0=Qf04L3N3M2N2N2O1N2N2O1N101O0O2O1O0000000O11O00000O10001O0O101O1N1O2O1N2M3N3L4L5K6HjWU8"}, "area": 1295, "bbox": [867, 311, 41, 41], "iscrowd": 0}, {"image_id": 47, "category_id": 1, "id": 47, "segmentation": {"size": [720, 1280], "counts": "gh[c07Vf08I3M4M2M3N2N2O1N2O1N101O001N101O0000000000000000O2O00000O2O0O2O0O2N2N2N2N3M2M5Jn\\k7"}, "area": 1315, "bbox": [881, 312, 41, 40], "iscrowd": 0}, {"image_id": 48, "category_id": 1, "id": 48, "segmentation": {"size": [720, 1280], "counts": "WZfc0:Sf07K2M3N2N2N2N2O2M2O1N101O0O101O0000000000000000O101O001N101O001N2N2N2N2M3N3L4K8FYk`7"}, "area": 1255, "bbox": [896, 314, 41, 39], "iscrowd": 0}, {"image_id": 49, "category_id": 1, "id": 49, "segmentation": {"size": [720, 1280], "counts": "iQnc08Vf06J4L4M2N3M1O2O1N2N2O0O2O0O2O0000000000000000000001N10001O0O2O1O0O2N2N2O2L3M4L4JkSY7"}, "area": 1282, "bbox": [907, 315, 41, 39], "iscrowd": 0}, {"image_id": 50, "category_id": 1, "id": 50, "segmentation": {"size": [720, 1280], "counts": "neSd06Vf08J4M3M3L4M2N1O2O0O101N2O0O100000000O1000000001O0O1000001O0O101O0O2O0O2O1N2N2O2M5K7FcRR7"}, "area": 1343, "bbox": [915, 317, 43, 39], "iscrowd": 0}, {"image_id": 51, "category_id": 1, "id": 51, "segmentation": {"size": [720, 1280], "counts": "`][d0=oe06L4L3N1O2O1N2N2O1N101N10000O2O00000000000000O101O0000000O2O001N2N2N2N2O1N3M2N3M3KcQk6"}, "area": 1361, "bbox": [926, 321, 42, 40], "iscrowd": 0}, {"image_id": 52, "category_id": 1, "id": 52, "segmentation": {"size": [720, 1280], "counts": "Rhad06Wf06I8K2M3N2N2N2O0O2N101N101O0O10000000000000000000000001O001N2O001N2O0O2O0O2N2O1M6JTgd6"}, "area": 1325, "bbox": [935, 321, 42, 38], "iscrowd": 0}, {"image_id": 53, "category_id": 1, "id": 53, "segmentation": {"size": [720, 1280], "counts": "aRhd0;Sf06J3M3N2N2N1O2N1O2O0O2O1N101O0O2O00000O100000000001N1000001O0O2O1O001N2N1O2N3M2M4L4K6Jao\\6"}, "area": 1412, "bbox": [944, 321, 44, 41], "iscrowd": 0}, {"image_id": 54, "category_id": 1, "id": 54, "segmentation": {"size": [720, 1280], "counts": "W]nd07Tf09J3N2M3N1N3N2O1N2N2O0O2O0O100000000O100001O000000000O100O2O001O001O001N2O0O2M4L3N3M3L6DbnU6"}, "area": 1378, "bbox": [953, 324, 45, 39], "iscrowd": 0}, {"image_id": 55, "category_id": 1, "id": 55, "segmentation": {"size": [720, 1280], "counts": "jgTe02Wf0;J5L3L3N2N2N1O2N1O2N1O101N100000001O000000000000000001O00001O000O2O001N2O0O2O1N2N2N3L4K6H`mn5"}, "area": 1448, "bbox": [962, 325, 46, 39], "iscrowd": 0}, {"image_id": 56, "category_id": 1, "id": 56, "segmentation": {"size": [720, 1280], "counts": "gh[e0;Rf05L4L3N2M3N1O2N2N3N2N0O2O00000O10001O00000000000000000001O01OO2N1O2N1O2M3N2K6K6FU]k5"}, "area": 1421, "bbox": [972, 327, 41, 43], "iscrowd": 0}, {"image_id": 57, "category_id": 1, "id": 57, "segmentation": {"size": [720, 1280], "counts": "h\\ae08Vf06I4N3L3N1O2N2N1O2N2O1N2O0O10000O2O00000000000000O100N2O2M2O2N2M5Ekfj5"}, "area": 1094, "bbox": [980, 327, 34, 40], "iscrowd": 0}, {"image_id": 58, "category_id": 1, "id": 58, "segmentation": {"size": [720, 1280], "counts": "Z_\\e06Wf05I7L3M3M3M2O1O2N1O101N1O2O0O101N10001O0O10000000001O01O000000000O2N1N3M2N3M2M5F9I^Pj5"}, "area": 1447, "bbox": [973, 321, 42, 44], "iscrowd": 0}, {"image_id": 59, "category_id": 1, "id": 59, "segmentation": {"size": [720, 1280], "counts": "_[Ze08Uf06J6L2M3M3N2N2N2O0O2O1N101O0O2O0000000O10001O000001N10001O0001O01N101O1N101N2N2L4K7F^]k5"}, "area": 1500, "bbox": [970, 317, 43, 43], "iscrowd": 0}, {"image_id": 60, "category_id": 1, "id": 60, "segmentation": {"size": [720, 1280], "counts": "aTVe02Yf0:H5L4M2M3N2N2N2O1N1O2O0O2O1N100O2O0000000000000000000000O101O0O101N1O2O0O2O1N2N2M4M2M5K5Ih`m5"}, "area": 1518, "bbox": [964, 316, 46, 42], "iscrowd": 0}, {"image_id": 61, "category_id": 1, "id": 61, "segmentation": {"size": [720, 1280], "counts": "PdRe07Sf09J5L3N2M3N2O1N2N2O0O2O1O0O101N1000001O0000000000O1000000O2O000O2O0O2O1N2N101N3M2M4L4L4KhgQ6"}, "area": 1538, "bbox": [959, 316, 45, 43], "iscrowd": 0}, {"image_id": 62, "category_id": 1, "id": 62, "segmentation": {"size": [720, 1280], "counts": "^Sod0<Qf05K5M3M2M3O1N2N2O0O2O1O0O2O000O101O0000000000000000O1000001N100O101N2O0O2N2N2N2N2M3N3M4IWXU6"}, "area": 1531, "bbox": [954, 319, 45, 42], "iscrowd": 0}, {"image_id": 63, "category_id": 1, "id": 63, "segmentation": {"size": [720, 1280], "counts": "cljd0:Tf05K4L4M2N2M3N2N2N101N101N2O1N1000001O00000000000000O1000001N100O2O0O2N2N2O1N2N2N2M3N3L5KP_Y6"}, "area": 1531, "bbox": [948, 323, 45, 43], "iscrowd": 0}, {"image_id": 64, "category_id": 1, "id": 64, "segmentation": {"size": [720, 1280], "counts": "gRhd0;Rf06K4M2N2M3N1O2N2N2N1O2O0O2O00001O0000000000000000000001O000O2O000O2N2O1N2N2N2N2N3M2L5L7GjX\\6"}, "area": 1473, "bbox": [944, 327, 45, 41], "iscrowd": 0}, {"image_id": 65, "category_id": 1, "id": 65, "segmentation": {"size": [720, 1280], "counts": "hefd04Uf0;J4L4L3N2N2O1N2N101N2O0O2O000O1000000O100000000001O0000000O2O0O2O1N102M2O1N1N3N2M4L4L7Gne]6"}, "area": 1447, "bbox": [942, 323, 45, 41], "iscrowd": 0}, {"image_id": 66, "category_id": 1, "id": 66, "segmentation": {"size": [720, 1280], "counts": "Toed06Vf09H5L4M2N2N2N2N2O0O2N101N101N101O000O10000000O101O0000001N101O0O101N101N2O1N2N2M3N3L4K6Ib\\^6"}, "area": 1497, "bbox": [941, 321, 45, 43], "iscrowd": 0}, {"image_id": 67, "category_id": 1, "id": 67, "segmentation": {"size": [720, 1280], "counts": "bXed0;Qf07K4L4M2N2N2O0O2O1N1O2O0O2O000O2O0000000000000000O101O00000O2O0O101N2O0O2O1N2N3L3N2L6Jci_6"}, "area": 1499, "bbox": [940, 322, 44, 42], "iscrowd": 0}, {"image_id": 68, "category_id": 1, "id": 68, "segmentation": {"size": [720, 1280], "counts": "hkcd05Vf09I5L4M3L2O2N2O1N2N101O0O2O001O0O1000000000000000000000O2O001N101N101N2N2N101N2N3L4L5I`Va6"}, "area": 1448, "bbox": [938, 325, 44, 41], "iscrowd": 0}, {"image_id": 69, "category_id": 1, "id": 69, "segmentation": {"size": [720, 1280], "counts": "ZUcd07Tf08K5K4M2M3N2N3M3N1N101N100O2O0000000O10000000O10001O0O10001O0O2N101N2O0O2N2N2N2N3L4M5Ikla6"}, "area": 1524, "bbox": [937, 327, 44, 44], "iscrowd": 0}, {"image_id": 70, "category_id": 1, "id": 70, "segmentation": {"size": [720, 1280], "counts": "b^bd0?oe06K3M2N2M3N3M102M2O1N101O000O2O0000000000O100O10000O101O0O2O0O2N101N2N2N2N3M3L4M4K\\Pd6"}, "area": 1472, "bbox": [936, 326, 42, 44], "iscrowd": 0}, {"image_id": 71, "category_id": 1, "id": 71, "segmentation": {"size": [720, 1280], "counts": "aQad0?oe05L3L5L2N2O1N3M3N1N100O2O00001O0O10000000000001O0O1O1O101N100O2N101N2N2N2N2N3L4L4M5Hmfd6"}, "area": 1521, "bbox": [934, 325, 43, 45], "iscrowd": 0}, {"image_id": 72, "category_id": 1, "id": 72, "segmentation": {"size": [720, 1280], "counts": "Vn^d08Uf09H4L4M3M2N3N1N2N2N2O0O2O000O100000001O00000000000000O2N1N201N101N101N2N2N3M2N3L5K6G\\jf6"}, "area": 1490, "bbox": [931, 327, 43, 44], "iscrowd": 0}, {"image_id": 73, "category_id": 1, "id": 73, "segmentation": {"size": [720, 1280], "counts": "Ua]d0=Qf05K4M2N3M2N2N3M2N2O1N1O2O0O101O000000000000001O0000000001N100O2N1N3O1N2N2M3M3N2N3M3L6Hl`g6"}, "area": 1560, "bbox": [929, 327, 44, 45], "iscrowd": 0}, {"image_id": 74, "category_id": 1, "id": 74, "segmentation": {"size": [720, 1280], "counts": "VT\\d0:Tf06J5K4M2N2N2N3M2N2O1N100O2O000O101O00000000000000000001O00001O0O2N2M3N2N2N2N2M5_OXZO2Wf0KbZj6"}, "area": 1498, "bbox": [927, 327, 42, 44], "iscrowd": 0}, {"image_id": 75, "category_id": 1, "id": 75, "segmentation": {"size": [720, 1280], "counts": "WgZd06Wf09H5L3M3L3N2N2O2M1O2O1N10001N100O101O0000000000000001O00001O001O0oNP[Oa0Qe0^OQ[O`0Qe0^OR[O>Qe0AQ[O;Re0BR[O;ce0M3N2Mo]l6"}, "area": 1368, "bbox": [925, 327, 41, 44], "iscrowd": 0}, {"image_id": 76, "category_id": 1, "id": 76, "segmentation": {"size": [720, 1280], "counts": "WZYd06Wf08I6K3L3N2N3N1N3M2O0O101N101O0O10000O1001O01O0008H2N1O2M2O2N1O1O1O1N2N2N2M2M4N1NRkm6"}, "area": 1224, "bbox": [923, 327, 41, 44], "iscrowd": 0}, {"image_id": 77, "category_id": 1, "id": 77, "segmentation": {"size": [720, 1280], "counts": "WmWd0:Sf06L4L2M3N2N2N3M2O1N2N2O0O100O2O0000000001O2N2N2N2N1O1O1O001O1N2O1N2O1O1N2N2M2M4M2Ocan6"}, "area": 1238, "bbox": [921, 328, 42, 42], "iscrowd": 0}, {"image_id": 78, "category_id": 1, "id": 78, "segmentation": {"size": [720, 1280], "counts": "fVWd0<Rf06K2N3M2M3N2N3M2N2N1O2O0O101O0O10000000000002N3M2N2N1O1O1N2O1N2O2M2O1N2N1N3M3N2M4KSXo6"}, "area": 1265, "bbox": [920, 327, 42, 43], "iscrowd": 0}, {"image_id": 79, "category_id": 1, "id": 79, "segmentation": {"size": [720, 1280], "counts": "T^[d0:Qf06J6K4N2M4L3N2N2O1O2O000O10000000O2O00001N100O2lNjZOl0Ve0SOnZOi0_e0N1N3M2N2M3N2N3KTeP7"}, "area": 1046, "bbox": [926, 327, 34, 43], "iscrowd": 0}, {"image_id": 80, "category_id": 1, "id": 80, "segmentation": {"size": [720, 1280], "counts": "nefd0?`e0BcZOm0Xe07O2O001OO2O0O101O2M3M2N2M3ZOZZO?oe0L2M5Jeno6"}, "area": 555, "bbox": [942, 329, 19, 40], "iscrowd": 0}, {"image_id": 81, "category_id": 1, "id": 81, "segmentation": {"size": [720, 1280], "counts": "`fSd03[f03M5L2O1N2N2O20O1O3M2N1O1M3Nfge7"}, "area": 194, "bbox": [915, 345, 15, 25], "iscrowd": 0}, {"image_id": 82, "category_id": 1, "id": 82, "segmentation": {"size": [720, 1280], "counts": "ffSd01^f02M2O2N2O2M2N3M2O0O2O0O2N100O1O10000010O2N2@WZO5Sf0O1O2M4M3Mob\\7"}, "area": 434, "bbox": [915, 345, 28, 26], "iscrowd": 0}, {"image_id": 83, "category_id": 1, "id": 83, "segmentation": {"size": [720, 1280], "counts": "i`Vd02^f02M3N1N2O0O2O0O1O100O2O0O100O1O100O100O1O100O2O000000O102N2DUZONoe0MhoV7"}, "area": 516, "bbox": [919, 348, 32, 24], "iscrowd": 0}, {"image_id": 84, "category_id": 1, "id": 84, "segmentation": {"size": [720, 1280], "counts": "oT\\d02]f02N1O2O0O10000O100O1000001N1000000O10000O100O1O1O1000O100O0HRZONngR7"}, "area": 347, "bbox": [927, 354, 31, 18], "iscrowd": 0}, {"image_id": 85, "category_id": 1, "id": 85, "segmentation": {"size": [720, 1280], "counts": "X_oc01^f04I5N2N1O1O1O1N2SZO@ie0>6O0O110O010O10O10O100O100O1O10000O100O10001N101N1O2Mdn40bcP7"}, "area": 409, "bbox": [909, 327, 44, 38], "iscrowd": 0}, {"image_id": 86, "category_id": 1, "id": 86, "segmentation": {"size": [720, 1280], "counts": "hUPd09Rf08K4M1O0O2O1O10O0010O00100000O010O10000O100O10000O100O2O0O2N10001N2O1N2N2N2O1N3MooV7"}, "area": 815, "bbox": [910, 327, 41, 31], "iscrowd": 0}, {"image_id": 87, "category_id": 1, "id": 87, "segmentation": {"size": [720, 1280], "counts": "khnc01Yf0<G6L3L4M2N2N2O1N3M2O0O2O0O2O000O10001O00000000000000O100O2O0O2N1O2O1N2N2N2N1O3M2N4K5J\\YV7"}, "area": 1505, "bbox": [908, 327, 44, 44], "iscrowd": 0}, {"image_id": 88, "category_id": 1, "id": 88, "segmentation": {"size": [720, 1280], "counts": "XRnc07Vf06J6L3L3N3M1O2O1N2N3N0O101N101O0O1000000000000000000001N10001O0O2O0O2O1N2N1O3L3N2M5K5JloV7"}, "area": 1471, "bbox": [907, 327, 44, 42], "iscrowd": 0}, {"image_id": 89, "category_id": 1, "id": 89, "segmentation": {"size": [720, 1280], "counts": "h[mc02[f0:G5K5K3N2N2N2O1N2N2N2O001N10001N10000000000000O1000001O0O10001N2O0O2O0O2N2N2M3N3M3K7I\\fW7"}, "area": 1449, "bbox": [906, 327, 44, 42], "iscrowd": 0}, {"image_id": 90, "category_id": 1, "id": 90, "segmentation": {"size": [720, 1280], "counts": "Welc09Tf07J4M2M3N3M2N2O1N2N2O0O2O0O101O0O1000000000000000000001O00000O2O0O2O0O2N2N2N2N2M4M3K6Kl\\X7"}, "area": 1499, "bbox": [905, 327, 44, 42], "iscrowd": 0}, {"image_id": 91, "category_id": 1, "id": 91, "segmentation": {"size": [720, 1280], "counts": "hnkc08Uf06K4L4M2N2M3N3N1N2N2O1N100O101O000O100000000000000001O0O10001O0O2O0O2O0O2N2N2M4M3L4L5I]SY7"}, "area": 1473, "bbox": [904, 327, 44, 42], "iscrowd": 0}, {"image_id": 92, "category_id": 1, "id": 92, "segmentation": {"size": [720, 1280], "counts": "ZXkc06Uf08K4L4M2N2M3O1N2N3M2O0O2O0O1000001N1000000000000000O2O0000001N101O001N2N1O2N2M4M3L3M4KniY7"}, "area": 1466, "bbox": [903, 327, 44, 42], "iscrowd": 0}, {"image_id": 93, "category_id": 1, "id": 93, "segmentation": {"size": [720, 1280], "counts": "lajc03Wf09J5M3L4M2N2N2N2N2N3N0O101N1000001N1000000000000000O101O00001N101O001N1O2O1N2M4L3N3L4K8HiiY7"}, "area": 1469, "bbox": [902, 327, 45, 42], "iscrowd": 0}, {"image_id": 94, "category_id": 1, "id": 94, "segmentation": {"size": [720, 1280], "counts": "gajc0;Qf07L3L3N2M3O1N2N2N2N2O001N10000O10001O0000O1000000000001N101O001N101O0O2O1N2M4L3N3L5JmV[7"}, "area": 1454, "bbox": [902, 327, 43, 42], "iscrowd": 0}, {"image_id": 95, "category_id": 1, "id": 95, "segmentation": {"size": [720, 1280], "counts": "\\kic03Uf0=I4L3N2N2M4N1N2N2N2O000O2O0O100000000000000000O1000001N10001N101O001N2O1N2M4M2N2M5J^m[7"}, "area": 1426, "bbox": [901, 327, 43, 41], "iscrowd": 0}, {"image_id": 96, "category_id": 1, "id": 96, "segmentation": {"size": [720, 1280], "counts": "Vkic0<Pf07L3L3N2N2N2N2N2N2O1N10001N10000000000000000000O1000001N101O000O2O001N2N2N3M2M4M2M7E^m[7"}, "area": 1437, "bbox": [901, 327, 43, 41], "iscrowd": 0}, {"image_id": 97, "category_id": 1, "id": 97, "segmentation": {"size": [720, 1280], "counts": "gTic0:Rf07K5L2M3N2N2N2N101N2N2O000O101O000000000000000000O1000001N101O0O2O001N2N2N3M2N2M4K5Knc\\7"}, "area": 1436, "bbox": [900, 327, 43, 41], "iscrowd": 0}, {"image_id": 98, "category_id": 1, "id": 98, "segmentation": {"size": [720, 1280], "counts": "ZQgc07Sf09J5M3L3N2N2N2N2O1N2N10001N100000000000000000O10000O2O00000O2O1N101N101N3M2N2M3M5J;FVg^7"}, "area": 1401, "bbox": [897, 327, 43, 41], "iscrowd": 0}, {"image_id": 99, "category_id": 1, "id": 99, "segmentation": {"size": [720, 1280], "counts": "Xc^c08Uf08H6K3N2N3M2N2N2O1N2N101O0O100000000000001O00O100000001O0O2O000O2N2N2O1N2M3M3N2N4Jnkg7"}, "area": 1461, "bbox": [885, 328, 42, 43], "iscrowd": 0}, {"image_id": 100, "category_id": 1, "id": 100, "segmentation": {"size": [720, 1280], "counts": "XUVc0<Qf05L4L3N3M2N2N2N2N3N1O0O100O2O0000000000000000O1000001O00001N101N2O0O2N2O1N2M3M4L4K6JZco7"}, "area": 1450, "bbox": [873, 329, 43, 42], "iscrowd": 0}, {"image_id": 101, "category_id": 1, "id": 101, "segmentation": {"size": [720, 1280], "counts": "i]nb0;Qf07K4M2N3M2N2O1N2N3N0O2O0O101N1000000000000000000000O1000001O0O2O001N102M2N2M3M3M5K4JlZW8"}, "area": 1481, "bbox": [862, 330, 43, 42], "iscrowd": 0}, {"image_id": 102, "category_id": 1, "id": 102, "segmentation": {"size": [720, 1280], "counts": "j\\gb0<Rf05J4N3L3N2N2N2N3N1N2N100O2O0O10000000000000000000000001N10001N2O0O2O1N101N2N2N2M4K5K7HYe]8"}, "area": 1527, "bbox": [852, 330, 44, 43], "iscrowd": 0}, {"image_id": 103, "category_id": 1, "id": 103, "segmentation": {"size": [720, 1280], "counts": "YRab0?oe04L4L4M2N2O1N2N2N3N0O100O2O00000O100000000000000000O2O000O2O1O0O2O001N2N2M3N3L4K4M6IWfd8"}, "area": 1495, "bbox": [843, 331, 43, 43], "iscrowd": 0}, {"image_id": 104, "category_id": 1, "id": 104, "segmentation": {"size": [720, 1280], "counts": "\\QZb0;Qf05N3L4L4M2N2N2N3N2M100O2O0O101O000O10000000000001O000O2O001N101O0O2O0O2N1O2N2M4M3K4M5IiPk8"}, "area": 1526, "bbox": [833, 331, 44, 44], "iscrowd": 0}, {"image_id": 105, "category_id": 1, "id": 105, "segmentation": {"size": [720, 1280], "counts": "\\]Tb09Tf07J6K2M4M2N2N2N2O1N101N100O2O000O1000000000000000000001O00001N101O0O2N2N2O1N2M3M4M3K8FgdP9"}, "area": 1540, "bbox": [825, 332, 44, 43], "iscrowd": 0}, {"image_id": 106, "category_id": 1, "id": 106, "segmentation": {"size": [720, 1280], "counts": "\\ina0<Rf04K6K3M4M2O1N2N2O1N2O001N101N1000000O1000000000000001O0O10001O0O2O0O2N101N2N1N3N4K5K5IhXV9"}, "area": 1574, "bbox": [817, 332, 44, 44], "iscrowd": 0}, {"image_id": 107, "category_id": 1, "id": 107, "segmentation": {"size": [720, 1280], "counts": "lkia0=Qf05K4L4M2M3N2N3N1N101N2O000O1000001O0000000000O100000000O2O000O101N2N101N2N3L3M4M3K5Kgl[9"}, "area": 1507, "bbox": [810, 334, 43, 43], "iscrowd": 0}, {"image_id": 108, "category_id": 1, "id": 108, "segmentation": {"size": [720, 1280], "counts": "lWda0=Qf04L5K3N3M2N2N2N2O1N2O1N100O101O00000O1000O100000001O000O10001N101O0O2O0O2N2M3N2M4L5J7GWj`9"}, "area": 1541, "bbox": [802, 333, 44, 44], "iscrowd": 0}, {"image_id": 109, "category_id": 1, "id": 109, "segmentation": {"size": [720, 1280], "counts": "\\Z_a0>oe06K4M2M4M2N2O1N2N2O001N10000O2O00000000000O11O0O10001O000O2O0O101N101N2N2N2M4L3N4K4JW^f9"}, "area": 1509, "bbox": [795, 333, 43, 44], "iscrowd": 0}, {"image_id": 110, "category_id": 1, "id": 110, "segmentation": {"size": [720, 1280], "counts": "\\fYa0?ne05M3L3N3M2N2N2O0O2O1N2O0O101O000O100000000000000000O2O0000001N101N2O0O2N2N2M4M2M4L4K8Fd[k9"}, "area": 1521, "bbox": [787, 334, 44, 43], "iscrowd": 0}], "categories": [{"id": 1, "name": "ball"}]}